pyplatform/datawarehouse/__init__.py
pyplatform/datawarehouse/datawarehouse.py
pyplatform_datawarehouse-2020.12.1.dist-info/METADATA
pyplatform_datawarehouse-2020.12.1.dist-info/WHEEL
pyplatform_datawarehouse-2020.12.1.dist-info/top_level.txt
pyplatform_datawarehouse-2020.12.1.dist-info/RECORD
